{
    "type": "minecraft:crafting_shaped",
    "pattern": [
        "RWR",
        "ITI",
        "ROR"
    ],
    "key": {
        "T": {
            "item": "naturesaura:conversion_catalyst"
        },
        "R": {
            "item": "minecraft:redstone_block"
        },
        "I": {
            "item": "naturesaura:sky_ingot"
        },
        "W": {
            "item": "naturesaura:token_fear"
        },
        "O": {
            "item": "naturesaura:token_anger"
        }
    },
    "result": {
        "item": "naturesaura:rf_converter"
    },
    "conditions": [
        {
            "type": "forge:item_exists",
            "item": "naturesaura:rf_converter"
        }
    ]
}